ho_protocols/__init__.py
ho_protocols/common_pb2.py
ho_protocols/common_pb2.pyi
ho_protocols/data_in_pb2.py
ho_protocols/data_in_pb2.pyi
ho_protocols/example_pb2.py
ho_protocols/example_pb2.pyi
ho_protocols/alert/__init__.py
ho_protocols/alert/alert_pb2.py
ho_protocols/alert/alert_pb2.pyi
ho_protocols/alert/bees_pb2.py
ho_protocols/alert/bees_pb2.pyi
ho_protocols/alert/system_pb2.py
ho_protocols/alert/system_pb2.pyi
ho_protocols/cmd/__init__.py
ho_protocols/cmd/cmd_pb2.py
ho_protocols/cmd/cmd_pb2.pyi
ho_protocols/live/__init__.py
ho_protocols/live/actuators_pb2.py
ho_protocols/live/actuators_pb2.pyi
ho_protocols/live/live_pb2.py
ho_protocols/live/live_pb2.pyi
ho_protocols/live/models_pb2.py
ho_protocols/live/models_pb2.pyi
ho_protocols/live/sensors_pb2.py
ho_protocols/live/sensors_pb2.pyi
ho_protocols/live/system_pb2.py
ho_protocols/live/system_pb2.pyi
ho_protocols/map/__init__.py
ho_protocols/map/map_pb2.py
ho_protocols/map/map_pb2.pyi
ho_protocols/query/__init__.py
ho_protocols/query/query_pb2.py
ho_protocols/query/query_pb2.pyi
ho_protocols-0.2.8.dist-info/LICENCE
ho_protocols-0.2.8.dist-info/METADATA
ho_protocols-0.2.8.dist-info/WHEEL
ho_protocols-0.2.8.dist-info/top_level.txt
ho_protocols-0.2.8.dist-info/RECORD
