Metadata-Version: 2.1
Name: ho-protocols
Version: 0.2.8
Summary: ProtoBuf definitions for HO components
Home-page: https://github.com/hiveopolis/ho-protocols
Classifier: Programming Language :: Python :: 3.8
Classifier: Operating System :: OS Independent
Classifier: License :: OSI Approved :: MIT License
Requires-Python: >=3.8
License-File: LICENCE
Requires-Dist: protobuf (~=4.22.0)
